{
    "name": "Simple Oval",
    "closed": true,
    "width": 12.0,
    "points": [
        {
            "x": -250.0,
            "y": -80.0
        },
        {
            "x": -225.0,
            "y": -80.0
        },
        {
            "x": -200.0,
            "y": -80.0
        },
        {
            "x": -175.0,
            "y": -80.0
        },
        {
            "x": -150.0,
            "y": -80.0
        },
        {
            "x": -125.0,
            "y": -80.0
        },
        {
            "x": -100.0,
            "y": -80.0
        },
        {
            "x": -75.0,
            "y": -80.0
        },
        {
            "x": -50.0,
            "y": -80.0
        },
        {
            "x": -25.0,
            "y": -80.0
        },
        {
            "x": 0.0,
            "y": -80.0
        },
        {
            "x": 25.0,
            "y": -80.0
        },
        {
            "x": 50.0,
            "y": -80.0
        },
        {
            "x": 75.0,
            "y": -80.0
        },
        {
            "x": 100.0,
            "y": -80.0
        },
        {
            "x": 125.0,
            "y": -80.0
        },
        {
            "x": 150.0,
            "y": -80.0
        },
        {
            "x": 175.0,
            "y": -80.0
        },
        {
            "x": 200.0,
            "y": -80.0
        },
        {
            "x": 225.0,
            "y": -80.0
        },
        {
            "x": 250.0,
            "y": -80.0
        },
        {
            "x": 258.362277,
            "y": -79.561752
        },
        {
            "x": 266.632935,
            "y": -78.251808
        },
        {
            "x": 274.72136,
            "y": -76.084521
        },
        {
            "x": 282.538931,
            "y": -73.083637
        },
        {
            "x": 290.0,
            "y": -69.282032
        },
        {
            "x": 297.02282,
            "y": -64.72136
        },
        {
            "x": 303.530449,
            "y": -59.451586
        },
        {
            "x": 309.451586,
            "y": -53.530449
        },
        {
            "x": 314.72136,
            "y": -47.02282
        },
        {
            "x": 319.282032,
            "y": -40.0
        },
        {
            "x": 323.083637,
            "y": -32.538931
        },
        {
            "x": 326.084521,
            "y": -24.72136
        },
        {
            "x": 328.251808,
            "y": -16.632935
        },
        {
            "x": 329.561752,
            "y": -8.362277
        },
        {
            "x": 330.0,
            "y": 0.0
        },
        {
            "x": 329.561752,
            "y": 8.362277
        },
        {
            "x": 328.251808,
            "y": 16.632935
        },
        {
            "x": 326.084521,
            "y": 24.72136
        },
        {
            "x": 323.083637,
            "y": 32.538931
        },
        {
            "x": 319.282032,
            "y": 40.0
        },
        {
            "x": 314.72136,
            "y": 47.02282
        },
        {
            "x": 309.451586,
            "y": 53.530449
        },
        {
            "x": 303.530449,
            "y": 59.451586
        },
        {
            "x": 297.02282,
            "y": 64.72136
        },
        {
            "x": 290.0,
            "y": 69.282032
        },
        {
            "x": 282.538931,
            "y": 73.083637
        },
        {
            "x": 274.72136,
            "y": 76.084521
        },
        {
            "x": 266.632935,
            "y": 78.251808
        },
        {
            "x": 258.362277,
            "y": 79.561752
        },
        {
            "x": 250.0,
            "y": 80.0
        },
        {
            "x": 225.0,
            "y": 80.0
        },
        {
            "x": 200.0,
            "y": 80.0
        },
        {
            "x": 175.0,
            "y": 80.0
        },
        {
            "x": 150.0,
            "y": 80.0
        },
        {
            "x": 125.0,
            "y": 80.0
        },
        {
            "x": 100.0,
            "y": 80.0
        },
        {
            "x": 75.0,
            "y": 80.0
        },
        {
            "x": 50.0,
            "y": 80.0
        },
        {
            "x": 25.0,
            "y": 80.0
        },
        {
            "x": 0.0,
            "y": 80.0
        },
        {
            "x": -25.0,
            "y": 80.0
        },
        {
            "x": -50.0,
            "y": 80.0
        },
        {
            "x": -75.0,
            "y": 80.0
        },
        {
            "x": -100.0,
            "y": 80.0
        },
        {
            "x": -125.0,
            "y": 80.0
        },
        {
            "x": -150.0,
            "y": 80.0
        },
        {
            "x": -175.0,
            "y": 80.0
        },
        {
            "x": -200.0,
            "y": 80.0
        },
        {
            "x": -225.0,
            "y": 80.0
        },
        {
            "x": -250.0,
            "y": 80.0
        },
        {
            "x": -258.362277,
            "y": 79.561752
        },
        {
            "x": -266.632935,
            "y": 78.251808
        },
        {
            "x": -274.72136,
            "y": 76.084521
        },
        {
            "x": -282.538931,
            "y": 73.083637
        },
        {
            "x": -290.0,
            "y": 69.282032
        },
        {
            "x": -297.02282,
            "y": 64.72136
        },
        {
            "x": -303.530449,
            "y": 59.451586
        },
        {
            "x": -309.451586,
            "y": 53.530449
        },
        {
            "x": -314.72136,
            "y": 47.02282
        },
        {
            "x": -319.282032,
            "y": 40.0
        },
        {
            "x": -323.083637,
            "y": 32.538931
        },
        {
            "x": -326.084521,
            "y": 24.72136
        },
        {
            "x": -328.251808,
            "y": 16.632935
        },
        {
            "x": -329.561752,
            "y": 8.362277
        },
        {
            "x": -330.0,
            "y": 0.0
        },
        {
            "x": -329.561752,
            "y": -8.362277
        },
        {
            "x": -328.251808,
            "y": -16.632935
        },
        {
            "x": -326.084521,
            "y": -24.72136
        },
        {
            "x": -323.083637,
            "y": -32.538931
        },
        {
            "x": -319.282032,
            "y": -40.0
        },
        {
            "x": -314.72136,
            "y": -47.02282
        },
        {
            "x": -309.451586,
            "y": -53.530449
        },
        {
            "x": -303.530449,
            "y": -59.451586
        },
        {
            "x": -297.02282,
            "y": -64.72136
        },
        {
            "x": -290.0,
            "y": -69.282032
        },
        {
            "x": -282.538931,
            "y": -73.083637
        },
        {
            "x": -274.72136,
            "y": -76.084521
        },
        {
            "x": -266.632935,
            "y": -78.251808
        },
        {
            "x": -258.362277,
            "y": -79.561752
        }
    ]
}
